HISTORY.md
LICENSE
MANIFEST.in
README.md
setup.py
camplight/__init__.py
camplight/api.py
camplight/cli.py
camplight/exceptions.py
camplight.egg-info/PKG-INFO
camplight.egg-info/SOURCES.txt
camplight.egg-info/dependency_links.txt
camplight.egg-info/entry_points.txt
camplight.egg-info/not-zip-safe
camplight.egg-info/requires.txt
camplight.egg-info/top_level.txt
rst/HISTORY.rst
rst/README.rst
test/__init__.py
test/test_campfire.py
test/test_room.py