Metadata-Version: 1.1
Name: camplight
Version: 0.9.6
Summary: Python implementation of the Campfire API
Home-page: https://github.com/mlafeldt/camplight
Author: Mathias Lafeldt
Author-email: mathias.lafeldt@gmail.com
License: MIT
Platform: UNKNOWN
Classifier: Development Status :: 5 - Production/Stable
Classifier: Intended Audience :: Developers
Classifier: Natural Language :: English
Classifier: License :: OSI Approved :: MIT License
Classifier: Operating System :: OS Independent
Classifier: Programming Language :: Python
Classifier: Programming Language :: Python :: 2.6
Classifier: Programming Language :: Python :: 2.7
Classifier: Programming Language :: Python :: 3.3
